log_mgr/__init__.py
log_mgr/logger.py
tests/__init__.py
tests/test_config.py
log_mgr-0.1.1.dist-info/METADATA
log_mgr-0.1.1.dist-info/WHEEL
log_mgr-0.1.1.dist-info/top_level.txt
log_mgr-0.1.1.dist-info/RECORD
